doms_json/__init__.py
doms_json-1.0.2.dist-info/licenses/LICENSE
doms_json-1.0.2.dist-info/METADATA
doms_json-1.0.2.dist-info/WHEEL
doms_json-1.0.2.dist-info/top_level.txt
doms_json-1.0.2.dist-info/RECORD
