Metadata-Version: 2.4
Name: doms-json
Version: 1.0.2
Summary: A JSON toolkit that's particularly useful for what I'm making
Author: Dominic Coletti
License: Apache-2.0
Project-URL: Homepage, https://github.com/DominicDJC/doms-json
Project-URL: Changelog, https://github.com/DominicDJC/doms-json/releases
Project-URL: Issues, https://github.com/DominicDJC/doms-json/issues
Project-URL: CI, https://github.com/DominicDJC/doms-json/actions
Classifier: License :: OSI Approved :: Apache Software License
Requires-Python: >=3.8
License-File: LICENSE
Provides-Extra: test
Requires-Dist: pytest; extra == "test"
Dynamic: license-file
